napcat/__init__.py
napcat/py.typed
napcat/api/models/__init__.py
napcat/api/models/arksharegroupapi.py
napcat/api/models/arksharegroupapi_audit_log.txt
napcat/api/models/arksharepeerapi.py
napcat/api/models/arksharepeerapi_audit_log.txt
napcat/api/models/botexitapi.py
napcat/api/models/botexitapi_audit_log.txt
napcat/api/models/cansendimageapi.py
napcat/api/models/cansendimageapi_audit_log.txt
napcat/api/models/cansendrecordapi.py
napcat/api/models/cansendrecordapi_audit_log.txt
napcat/api/models/checkurlsafelyapi.py
napcat/api/models/checkurlsafelyapi_audit_log.txt
napcat/api/models/clickinlinekeyboardbuttonapi.py
napcat/api/models/clickinlinekeyboardbuttonapi_audit_log.txt
napcat/api/models/createcollectionapi.py
napcat/api/models/createcollectionapi_audit_log.txt
napcat/api/models/creategroupfilefolderapi.py
napcat/api/models/creategroupfilefolderapi_audit_log.txt
napcat/api/models/deleteessencemsgapi.py
napcat/api/models/deleteessencemsgapi_audit_log.txt
napcat/api/models/deletefriendapi.py
napcat/api/models/deletefriendapi_audit_log.txt
napcat/api/models/deletegroupfileapi.py
napcat/api/models/deletegroupfileapi_audit_log.txt
napcat/api/models/deletegroupfolderapi.py
napcat/api/models/deletegroupfolderapi_audit_log.txt
napcat/api/models/deletemsgapi.py
napcat/api/models/deletemsgapi_audit_log.txt
napcat/api/models/delgroupnoticeapi.py
napcat/api/models/delgroupnoticeapi_audit_log.txt
napcat/api/models/downloadfileapi.py
napcat/api/models/downloadfileapi_audit_log.txt
napcat/api/models/fetchcustomfaceapi.py
napcat/api/models/fetchcustomfaceapi_audit_log.txt
napcat/api/models/fetchemojilikeapi.py
napcat/api/models/fetchemojilikeapi_audit_log.txt
napcat/api/models/fetchuserprofilelikeapi.py
napcat/api/models/fetchuserprofilelikeapi_audit_log.txt
napcat/api/models/forwardfriendsinglemsgapi.py
napcat/api/models/forwardfriendsinglemsgapi_audit_log.txt
napcat/api/models/forwardgroupsinglemsgapi.py
napcat/api/models/forwardgroupsinglemsgapi_audit_log.txt
pynapcat-4.7.43.dist-info/METADATA
pynapcat-4.7.43.dist-info/WHEEL
pynapcat-4.7.43.dist-info/licenses/LICENSE
pynapcat-4.7.43.dist-info/RECORD
