Metadata-Version: 2.4
Name: pynapcat
Version: 4.7.43
Summary: From napcat.fastnc import FastNC
Author-email: LIghtJUNction <LIghtJUNction.me@gmail.com>
License-File: LICENSE
Requires-Python: >=3.13
Requires-Dist: dotenv>=0.9.9
Requires-Dist: httpx-ws>=0.7.2
Requires-Dist: openai-agents>=0.0.11
Requires-Dist: openai>=1.75.0
Requires-Dist: pydantic>=2.11.3
Requires-Dist: pyyaml>=6.0.2
Requires-Dist: toml>=0.10.2
Provides-Extra: dev
